{"version":1,"kind":"Notebook","sha256":"b9547518c99bae5cbb704389e1b1a20128215fe675118ee7ec4bda1dfa074ea2","slug":"external-notebooks.eurodatacube.notebooks.notebooks.contributions.drought-monitoring","location":"/external_notebooks/eurodatacube/notebooks/notebooks/contributions/Drought_Monitoring.ipynb","dependencies":[],"frontmatter":{"title":"Drought impact monitoring platform","content_includes_title":false,"kernelspec":{"name":"conda-env-edc-default-2022.10-14-py","display_name":"Python [conda env:edc-default-2022.10-14]","language":"python"},"github":"https://github.com/eurodatacube/example-viewer","subject":"Euro Data Cube Examples","numbering":{"title":{"offset":5}},"edit_url":"https://github.com/eurodatacube/example-viewer/blob/main/external_notebooks/eurodatacube/notebooks/notebooks/contributions/Drought_Monitoring.ipynb","thumbnail":"/example-viewer/build/ad5c19782b006f72352ae57794305840.png","exports":[{"format":"ipynb","filename":"Drought_Monitoring.ipynb","url":"/example-viewer/build/Drought_Monitoring-d9bb6efc7775e467a6681b954e2d5971.ipynb"}]},"widgets":{},"mdast":{"type":"root","children":[{"type":"block","kind":"notebook-content","data":{},"children":[{"type":"heading","depth":2,"position":{"start":{"line":3,"column":1},"end":{"line":3,"column":1}},"children":[{"type":"text","value":"EO based Digital Twin precursor of a spatio-temporal drought impact monitoring system in Europe","position":{"start":{"line":3,"column":1},"end":{"line":3,"column":1}},"key":"kWl7M5NUVD"}],"identifier":"eo-based-digital-twin-precursor-of-a-spatio-temporal-drought-impact-monitoring-system-in-europe","label":"EO based Digital Twin precursor of a spatio-temporal drought impact monitoring system in Europe","html_id":"eo-based-digital-twin-precursor-of-a-spatio-temporal-drought-impact-monitoring-system-in-europe","implicit":true,"key":"TfGx7h5OAL"},{"type":"paragraph","position":{"start":{"line":5,"column":1},"end":{"line":5,"column":1}},"children":[{"type":"emphasis","position":{"start":{"line":5,"column":1},"end":{"line":5,"column":1}},"children":[{"type":"text","value":"Eva Ivits","position":{"start":{"line":5,"column":1},"end":{"line":5,"column":1}},"key":"k3cXAbZJki"},{"type":"superscript","children":[{"type":"text","value":"1","key":"oUpjM4BHEZ"}],"key":"xQlvJVFk4V"},{"type":"text","value":", Lars Eklundh","position":{"start":{"line":5,"column":1},"end":{"line":5,"column":1}},"key":"MwLaqGvAH7"},{"type":"superscript","children":[{"type":"text","value":"2","key":"MsOUb8cWdJ"}],"key":"hvXnUe89ex"},{"type":"text","value":", Roel Van Hoolst","position":{"start":{"line":5,"column":1},"end":{"line":5,"column":1}},"key":"PazWK9pKc2"},{"type":"superscript","children":[{"type":"text","value":"3","key":"rkonmpxody"}],"key":"tGuT0AD2pS"},{"type":"text","value":", Bruno Smets","position":{"start":{"line":5,"column":1},"end":{"line":5,"column":1}},"key":"U55CdsphkP"},{"type":"superscript","children":[{"type":"text","value":"3","key":"aW43Hr2vRG"}],"key":"mHGt18QRmJ"},{"type":"text","value":", Hongxiao, Zhanzhang","position":{"start":{"line":5,"column":1},"end":{"line":5,"column":1}},"key":"ebCKVu2zFo"},{"type":"superscript","children":[{"type":"text","value":"3","key":"X7Fn9Oo19Q"}],"key":"mpHqlQvp4J"},{"type":"text","value":", Grega Milcinski","position":{"start":{"line":5,"column":1},"end":{"line":5,"column":1}},"key":"pDZBYcEPni"},{"type":"superscript","children":[{"type":"text","value":"4","key":"GQA4Sn7j83"}],"key":"BM5JMAlKOC"},{"type":"text","value":", Anja Vrecko","position":{"start":{"line":5,"column":1},"end":{"line":5,"column":1}},"key":"ot1VvD3peM"},{"type":"superscript","children":[{"type":"text","value":"4","key":"NBHZZajSZq"}],"key":"XAtNlfuG5Z"},{"type":"text","value":", Maxim Lamare","position":{"start":{"line":5,"column":1},"end":{"line":5,"column":1}},"key":"Jh3MVVefif"},{"type":"superscript","children":[{"type":"text","value":"5","key":"c7dxA9fs9P"}],"key":"N5wAZ8RseX"}],"key":"KAz7b42poZ"}],"key":"p5eBjEa1yr"},{"type":"paragraph","position":{"start":{"line":9,"column":1},"end":{"line":13,"column":1}},"children":[{"type":"text","value":"1: European Environment Agency;\n2: Lund University;\n3: VITO;\n4: Sinergise;\n5: Sentinel Hub","position":{"start":{"line":9,"column":1},"end":{"line":9,"column":1}},"key":"P4HcwYIrCl"}],"key":"Gcjm1byvpk"}],"key":"OBTOjPtQYH"},{"type":"block","kind":"notebook-content","data":{},"children":[{"type":"heading","depth":2,"position":{"start":{"line":1,"column":1},"end":{"line":1,"column":1}},"children":[{"type":"text","value":"Introduction","position":{"start":{"line":1,"column":1},"end":{"line":1,"column":1}},"key":"Xtdzw01lPg"}],"identifier":"introduction","label":"Introduction","html_id":"introduction","implicit":true,"key":"jqj0nsjfb2"},{"type":"paragraph","position":{"start":{"line":3,"column":1},"end":{"line":3,"column":1}},"children":[{"type":"text","value":"This Jupyter Notebook presents the workflow developped within the ESA funded Drought impact monitoring platform pilot project. The aim of the project was to develop a pan-European scale drought impact monitoring platform using the new CLMS service High Resolution Vegetation Phenology and Productivity (HR-VPP) derived from Sentinel 2 images. The 10m spatial resolution seasonal trajectories and phenology and productivity parameters were used for studying vegetation dynamics as a response to soil moisture deficit during the period 2017-2020 in Europe. The project was initially based on the workflow developed within the framework of the EEA Drought Impact Indicator (EEA 2021).  However, during the development phase of the project, the scientific principles governing the algorithms were consolidated and an entirely new workflow was proposed.","position":{"start":{"line":3,"column":1},"end":{"line":3,"column":1}},"key":"exxdL3QAtU"}],"key":"Q7qYXzGcqK"},{"type":"paragraph","position":{"start":{"line":6,"column":1},"end":{"line":6,"column":1}},"children":[{"type":"text","value":"This Jupyter Notebook demonstrates how to derive the following variables based on the MR-VPP and HR-VPP datasets:","position":{"start":{"line":6,"column":1},"end":{"line":6,"column":1}},"key":"qq1LA1PNcr"}],"key":"T63mppZs8Q"},{"type":"list","ordered":false,"spread":false,"position":{"start":{"line":8,"column":1},"end":{"line":42,"column":1}},"children":[{"type":"listItem","spread":true,"position":{"start":{"line":8,"column":1},"end":{"line":9,"column":1}},"children":[{"type":"paragraph","position":{"start":{"line":8,"column":1},"end":{"line":8,"column":1}},"children":[{"type":"text","value":"Soil moisture anomaly","position":{"start":{"line":8,"column":1},"end":{"line":8,"column":1}},"key":"K5avAnmzfT"}],"key":"sgcs1Jfhoq"}],"key":"skT9PWXiJI"},{"type":"listItem","spread":true,"position":{"start":{"line":10,"column":1},"end":{"line":11,"column":1}},"children":[{"type":"paragraph","position":{"start":{"line":10,"column":1},"end":{"line":10,"column":1}},"children":[{"type":"text","value":"Long Term Average soil moisture anomaly","position":{"start":{"line":10,"column":1},"end":{"line":10,"column":1}},"key":"sWYmhI906C"}],"key":"oSDLQvEE6X"}],"key":"Iv7liA67g0"},{"type":"listItem","spread":true,"position":{"start":{"line":12,"column":1},"end":{"line":13,"column":1}},"children":[{"type":"paragraph","position":{"start":{"line":12,"column":1},"end":{"line":12,"column":1}},"children":[{"type":"text","value":"Monthly drought hazard","position":{"start":{"line":12,"column":1},"end":{"line":12,"column":1}},"key":"wp5EExvtgN"}],"key":"pkaZQ8FDtv"}],"key":"T3In7DZWQQ"},{"type":"listItem","spread":true,"position":{"start":{"line":14,"column":1},"end":{"line":15,"column":1}},"children":[{"type":"paragraph","position":{"start":{"line":14,"column":1},"end":{"line":14,"column":1}},"children":[{"type":"text","value":"Drought pressure","position":{"start":{"line":14,"column":1},"end":{"line":14,"column":1}},"key":"lCHcIvcJDt"}],"key":"h9NWIygXHs"}],"key":"Rr9za1cZsO"},{"type":"listItem","spread":true,"position":{"start":{"line":16,"column":1},"end":{"line":17,"column":1}},"children":[{"type":"paragraph","position":{"start":{"line":16,"column":1},"end":{"line":16,"column":1}},"children":[{"type":"text","value":"Drought pressure month","position":{"start":{"line":16,"column":1},"end":{"line":16,"column":1}},"key":"gTDdkTVqfb"}],"key":"IYZUbEf818"}],"key":"SuYbodc8QH"},{"type":"listItem","spread":true,"position":{"start":{"line":18,"column":1},"end":{"line":19,"column":1}},"children":[{"type":"paragraph","position":{"start":{"line":18,"column":1},"end":{"line":18,"column":1}},"children":[{"type":"text","value":"Drought pressure intensity","position":{"start":{"line":18,"column":1},"end":{"line":18,"column":1}},"key":"qn2ndHm19y"}],"key":"YnZ185KrBY"}],"key":"omSiEeuGpT"},{"type":"listItem","spread":true,"position":{"start":{"line":20,"column":1},"end":{"line":21,"column":1}},"children":[{"type":"paragraph","position":{"start":{"line":20,"column":1},"end":{"line":20,"column":1}},"children":[{"type":"text","value":"Long Term Average drought pressure intensity","position":{"start":{"line":20,"column":1},"end":{"line":20,"column":1}},"key":"W9ERKHb4r1"}],"key":"NspFb2Lcn4"}],"key":"E9I7Gct6KP"},{"type":"listItem","spread":true,"position":{"start":{"line":22,"column":1},"end":{"line":23,"column":1}},"children":[{"type":"paragraph","position":{"start":{"line":22,"column":1},"end":{"line":22,"column":1}},"children":[{"type":"text","value":"LINT anomaly","position":{"start":{"line":22,"column":1},"end":{"line":22,"column":1}},"key":"ivogCMXGlQ"}],"key":"PkekQSSrWT"}],"key":"QuVWN8ILDR"},{"type":"listItem","spread":true,"position":{"start":{"line":24,"column":1},"end":{"line":25,"column":1}},"children":[{"type":"paragraph","position":{"start":{"line":24,"column":1},"end":{"line":24,"column":1}},"children":[{"type":"text","value":"Drought impact","position":{"start":{"line":24,"column":1},"end":{"line":24,"column":1}},"key":"zjJEu4zOse"}],"key":"CoUnZaWsDm"}],"key":"AaBxmYTFZu"},{"type":"listItem","spread":true,"position":{"start":{"line":26,"column":1},"end":{"line":27,"column":1}},"children":[{"type":"paragraph","position":{"start":{"line":26,"column":1},"end":{"line":26,"column":1}},"children":[{"type":"text","value":"Drought impact mask","position":{"start":{"line":26,"column":1},"end":{"line":26,"column":1}},"key":"jmWYDVZx5F"}],"key":"ewrUh1vB6g"}],"key":"ve8TadNqwJ"},{"type":"listItem","spread":true,"position":{"start":{"line":28,"column":1},"end":{"line":29,"column":1}},"children":[{"type":"paragraph","position":{"start":{"line":28,"column":1},"end":{"line":28,"column":1}},"children":[{"type":"text","value":"Drought impact intensity","position":{"start":{"line":28,"column":1},"end":{"line":28,"column":1}},"key":"jCx2Rqxdwh"}],"key":"ke7MsgQ9R6"}],"key":"YyyMYAbqIq"},{"type":"listItem","spread":true,"position":{"start":{"line":30,"column":1},"end":{"line":31,"column":1}},"children":[{"type":"paragraph","position":{"start":{"line":30,"column":1},"end":{"line":30,"column":1}},"children":[{"type":"text","value":"Drought impact intensity mask","position":{"start":{"line":30,"column":1},"end":{"line":30,"column":1}},"key":"Av5wEmJ27W"}],"key":"q29gMWlJ9X"}],"key":"xH27Q7yeNi"},{"type":"listItem","spread":true,"position":{"start":{"line":32,"column":1},"end":{"line":33,"column":1}},"children":[{"type":"paragraph","position":{"start":{"line":32,"column":1},"end":{"line":32,"column":1}},"children":[{"type":"text","value":"TPROD anomaly","position":{"start":{"line":32,"column":1},"end":{"line":32,"column":1}},"key":"Jdom59csnU"}],"key":"Vnjr9yiUWp"}],"key":"VpYU86drMD"},{"type":"listItem","spread":true,"position":{"start":{"line":34,"column":1},"end":{"line":35,"column":1}},"children":[{"type":"paragraph","position":{"start":{"line":34,"column":1},"end":{"line":34,"column":1}},"children":[{"type":"text","value":"SPROD anomaly","position":{"start":{"line":34,"column":1},"end":{"line":34,"column":1}},"key":"GhaxrWujUJ"}],"key":"yuC9NZynCC"}],"key":"nXzODl0duM"},{"type":"listItem","spread":true,"position":{"start":{"line":36,"column":1},"end":{"line":37,"column":1}},"children":[{"type":"paragraph","position":{"start":{"line":36,"column":1},"end":{"line":36,"column":1}},"children":[{"type":"text","value":"Total drought impact","position":{"start":{"line":36,"column":1},"end":{"line":36,"column":1}},"key":"S48YUwFDKU"}],"key":"sRPjDHJzOW"}],"key":"KZPRUt9tQh"},{"type":"listItem","spread":true,"position":{"start":{"line":38,"column":1},"end":{"line":39,"column":1}},"children":[{"type":"paragraph","position":{"start":{"line":38,"column":1},"end":{"line":38,"column":1}},"children":[{"type":"text","value":"Seasonal drought impact","position":{"start":{"line":38,"column":1},"end":{"line":38,"column":1}},"key":"wwaQPx4VBT"}],"key":"fBDBnZuS7N"}],"key":"ma7X4I19ks"},{"type":"listItem","spread":true,"position":{"start":{"line":40,"column":1},"end":{"line":42,"column":1}},"children":[{"type":"paragraph","position":{"start":{"line":40,"column":1},"end":{"line":40,"column":1}},"children":[{"type":"text","value":"Number of Seasons","position":{"start":{"line":40,"column":1},"end":{"line":40,"column":1}},"key":"zegTOW1wyF"}],"key":"J6ChfjFJbV"}],"key":"ccrBVajKKY"}],"key":"Ul4IsIkqg5"},{"type":"paragraph","position":{"start":{"line":43,"column":1},"end":{"line":43,"column":1}},"children":[{"type":"text","value":"The variable are generated as raster files, accompanied by statistics aggregated by:","position":{"start":{"line":43,"column":1},"end":{"line":43,"column":1}},"key":"NkMEo37bxt"}],"key":"DNmMDrYeZQ"},{"type":"list","ordered":false,"spread":false,"position":{"start":{"line":45,"column":1},"end":{"line":51,"column":1}},"children":[{"type":"listItem","spread":true,"position":{"start":{"line":45,"column":1},"end":{"line":46,"column":1}},"children":[{"type":"paragraph","position":{"start":{"line":45,"column":1},"end":{"line":45,"column":1}},"children":[{"type":"text","value":"Adminstrative area (NUTS3 regions)","position":{"start":{"line":45,"column":1},"end":{"line":45,"column":1}},"key":"dY32nH9BKS"}],"key":"aikvEVGecv"}],"key":"jF0PUms5bT"},{"type":"listItem","spread":true,"position":{"start":{"line":47,"column":1},"end":{"line":48,"column":1}},"children":[{"type":"paragraph","position":{"start":{"line":47,"column":1},"end":{"line":47,"column":1}},"children":[{"type":"text","value":"Land Cover type","position":{"start":{"line":47,"column":1},"end":{"line":47,"column":1}},"key":"DmLcJpBWfW"}],"key":"S9WmcQdR5A"}],"key":"qhOiXkUMr1"},{"type":"listItem","spread":true,"position":{"start":{"line":49,"column":1},"end":{"line":51,"column":1}},"children":[{"type":"paragraph","position":{"start":{"line":49,"column":1},"end":{"line":49,"column":1}},"children":[{"type":"text","value":"Land Cover flow","position":{"start":{"line":49,"column":1},"end":{"line":49,"column":1}},"key":"b7EVzOa9G5"}],"key":"JboiqsFrZX"}],"key":"LEWG8FAkPp"}],"key":"imdiDUlUh3"},{"type":"paragraph","position":{"start":{"line":52,"column":1},"end":{"line":52,"column":1}},"children":[{"type":"text","value":"The workflow is designed to be run at the continental scale. However, for demonstration purposes, this example shows the workflow executed for a single NUTS3 region (Cádiz, Spain).","position":{"start":{"line":52,"column":1},"end":{"line":52,"column":1}},"key":"qgqyZXSVVe"}],"key":"R3sKCCT6H8"}],"key":"cTxgfD9GZA"},{"type":"block","kind":"notebook-content","data":{},"children":[{"type":"heading","depth":2,"position":{"start":{"line":1,"column":1},"end":{"line":1,"column":1}},"children":[{"type":"text","value":"Processing workflow","position":{"start":{"line":1,"column":1},"end":{"line":1,"column":1}},"key":"wRngwYGETM"}],"identifier":"processing-workflow","label":"Processing workflow","html_id":"processing-workflow","implicit":true,"key":"iE4Q2so3K3"},{"type":"paragraph","position":{"start":{"line":3,"column":1},"end":{"line":3,"column":1}},"children":[{"type":"text","value":"The following figure shows the processing workflow that is implemented in this Jupyter Notebook.","position":{"start":{"line":3,"column":1},"end":{"line":3,"column":1}},"key":"v84VVVdFIJ"}],"key":"Okp4yUg4Va"},{"type":"list","ordered":false,"spread":false,"position":{"start":{"line":5,"column":1},"end":{"line":11,"column":1}},"children":[{"type":"listItem","spread":true,"position":{"start":{"line":5,"column":1},"end":{"line":6,"column":1}},"children":[{"type":"paragraph","position":{"start":{"line":5,"column":1},"end":{"line":5,"column":1}},"children":[{"type":"text","value":"Dark green boxes represent raster inputs.","position":{"start":{"line":5,"column":1},"end":{"line":5,"column":1}},"key":"bKQTVAl7vY"}],"key":"drJa1QpoMH"}],"key":"idGWcZYKtt"},{"type":"listItem","spread":true,"position":{"start":{"line":7,"column":1},"end":{"line":8,"column":1}},"children":[{"type":"paragraph","position":{"start":{"line":7,"column":1},"end":{"line":7,"column":1}},"children":[{"type":"text","value":"Light green boxes represent raster outputs.","position":{"start":{"line":7,"column":1},"end":{"line":7,"column":1}},"key":"QahYoGjubc"}],"key":"Qk5ckiOnZr"}],"key":"hXrhCJUuJX"},{"type":"listItem","spread":true,"position":{"start":{"line":9,"column":1},"end":{"line":11,"column":1}},"children":[{"type":"paragraph","position":{"start":{"line":9,"column":1},"end":{"line":9,"column":1}},"children":[{"type":"text","value":"Dark grey boxes with a thick frame represent JSON outputs (statistics).","position":{"start":{"line":9,"column":1},"end":{"line":9,"column":1}},"key":"IDDot3lRV2"}],"key":"C652ccXKx7"}],"key":"aQ18nik4ka"}],"key":"kIQv9Wletn"},{"type":"image","url":"/example-viewer/build/ad5c19782b006f72352ae57794305840.png","alt":"Jupyter Notebook processing workflow","position":{"start":{"line":12,"column":1},"end":{"line":12,"column":1}},"key":"tVgICGmbXS","urlSource":"https://github.com/eurodatacube/notebooks/blob/master/notebooks/contributions/example_data/drought_monitoring/Drought_diagram.png?raw=true"}],"key":"PIr8rygbu5"},{"type":"block","kind":"notebook-content","data":{},"children":[{"type":"heading","depth":2,"position":{"start":{"line":1,"column":1},"end":{"line":1,"column":1}},"children":[{"type":"text","value":"Step 1: MR-VPP annual and monthly products","position":{"start":{"line":1,"column":1},"end":{"line":1,"column":1}},"key":"y2zKe7rBAe"}],"identifier":"step-1-mr-vpp-annual-and-monthly-products","label":"Step 1: MR-VPP annual and monthly products","html_id":"step-1-mr-vpp-annual-and-monthly-products","implicit":true,"key":"kitDJ9gYGK"},{"type":"paragraph","position":{"start":{"line":3,"column":1},"end":{"line":3,"column":1}},"children":[{"type":"text","value":"In a first step, we will compute the annual and monthly drought products based on Medium Resolution Vegetation Phenology and Productivity (MR-VPP).","position":{"start":{"line":3,"column":1},"end":{"line":3,"column":1}},"key":"g0VopZ8xa1"}],"key":"P6kQuDBrRk"}],"key":"SUMfIQCGz2"},{"type":"block","kind":"notebook-code","data":{},"children":[{"type":"code","lang":"python","executable":true,"value":"# Sentinel Hub\nfrom sentinelhub import (SHConfig, Geometry, SentinelHubRequest, DataCollection, MimeType, BBox, SentinelHubBatch, BatchRequestStatus)\n\n# Geospatial\nimport geopandas as gpd\nfrom shapely.geometry import shape, GeometryCollection\n\n# Utilities\nimport json\nimport time\nimport datetime as dt\nimport os\nimport urllib3","key":"Ns2oDuQG1x"},{"type":"output","id":"gD59jdOkJ_rEaUsQbBjpX","data":[],"key":"iyNMRvF1UT"}],"key":"U5OcLMAcjG"},{"type":"block","kind":"notebook-content","data":{},"children":[{"type":"heading","depth":3,"position":{"start":{"line":1,"column":1},"end":{"line":1,"column":1}},"children":[{"type":"text","value":"Credentials","position":{"start":{"line":1,"column":1},"end":{"line":1,"column":1}},"key":"IpuS59gSEh"}],"identifier":"credentials","label":"Credentials","html_id":"credentials","implicit":true,"key":"ts8sCiIe0f"},{"type":"paragraph","position":{"start":{"line":3,"column":1},"end":{"line":3,"column":1}},"children":[{"type":"text","value":"We recommend the use of EDC built-in credentials for Sentinel Hub services.","position":{"start":{"line":3,"column":1},"end":{"line":3,"column":1}},"key":"uz04879doC"}],"key":"CnnZNxjis3"}],"key":"E2kHrfqoF8"},{"type":"block","kind":"notebook-code","data":{},"children":[{"type":"code","lang":"python","executable":true,"value":"# Set the Sentinel Hub credentials based on EDC managed credentials\nconfig = SHConfig()\nconfig.sh_client_id = os.environ[\"SH_CLIENT_ID\"]\nconfig.sh_client_secret = os.environ[\"SH_CLIENT_SECRET\"]\n\n# Change endpoint\nconfig.sh_base_url  = \"https://creodias.sentinel-hub.com\"","key":"KWa6TDPpYV"},{"type":"output","id":"Up9asl_eDOuPNxSD07yGu","data":[],"key":"b1ACIrUdMh"}],"key":"t6rgHN7222"},{"type":"block","kind":"notebook-content","data":{},"children":[{"type":"heading","depth":3,"position":{"start":{"line":1,"column":1},"end":{"line":1,"column":1}},"children":[{"type":"text","value":"Read AOI","position":{"start":{"line":1,"column":1},"end":{"line":1,"column":1}},"key":"WeBqY7chn3"}],"identifier":"read-aoi","label":"Read AOI","html_id":"read-aoi","implicit":true,"key":"ZkR0ZJyRWo"},{"type":"paragraph","position":{"start":{"line":3,"column":1},"end":{"line":3,"column":1}},"children":[{"type":"text","value":"In the following cells we will specify the geoJSON of the AOI for Batch Processing. Here we will use the NUTS3 region of Cádiz in southern Spain.","position":{"start":{"line":3,"column":1},"end":{"line":3,"column":1}},"key":"Ykd8LB2sPs"}],"key":"D42vdBrOdk"}],"key":"pucBueOrGa"},{"type":"block","kind":"notebook-code","data":{},"children":[{"type":"code","lang":"python","executable":true,"value":"# Open Json\nfullaoi = gpd.read_file(\"https://raw.githubusercontent.com/eurodatacube/notebooks/master/notebooks/contributions/example_data/drought_monitoring/Cadiz.geojson\")\n\n# Buffer 500m to make sure the entire AOI is covered\nbuffered_aoi = fullaoi.iloc[0].geometry.buffer(500)\n\n# Check number of vertices (Sentinel Hub can only process geometries with < 1500 nodes)\nnodes = 0\nfor x in buffered_aoi.geoms:\n    nodes += len(x.exterior.coords)\n\n# If too many nodes, progressively simplify\nsim_nr = 100\n\nwhile nodes >= 1500:\n    \n    # Simplify geometry\n    buffered_aoi = fullaoi.iloc[0].geometry.buffer(500).simplify(sim_nr)\n    sim_nr += 100\n\n    # Recompute nodes\n    nodes = 0\n    for x in buffered_aoi.geoms:\n        nodes += len(x.exterior.coords)\n\ncadiz_aoi = Geometry(buffered_aoi, crs=\"EPSG:3035\")","key":"boJozieRM6"},{"type":"output","id":"hjOUSKkLrXeWLypwQzVR5","data":[],"key":"tmuCfNWjh9"}],"key":"PbnaEZFwnE"},{"type":"block","kind":"notebook-code","data":{},"children":[{"type":"code","lang":"python","executable":true,"value":"# Show the geometry\nbuffered_aoi","key":"kajKoHSnIa"},{"type":"output","id":"DE0UC2zOkmg2h9V8_mDi0","data":[],"key":"rOFwPYeaTe"}],"key":"QAbUn7CzTK"},{"type":"block","kind":"notebook-content","data":{},"children":[{"type":"heading","depth":2,"position":{"start":{"line":1,"column":1},"end":{"line":1,"column":1}},"children":[{"type":"text","value":"Evalscript for MR-VPP 500m products","position":{"start":{"line":1,"column":1},"end":{"line":1,"column":1}},"key":"kZBnaIyuJH"}],"identifier":"evalscript-for-mr-vpp-500m-products","label":"Evalscript for MR-VPP 500m products","html_id":"evalscript-for-mr-vpp-500m-products","implicit":true,"key":"LXJMIoTkxv"},{"type":"paragraph","position":{"start":{"line":3,"column":1},"end":{"line":3,"column":1}},"children":[{"type":"text","value":"The workflow was written as an ","position":{"start":{"line":3,"column":1},"end":{"line":3,"column":1}},"key":"dA3EoDLtGC"},{"type":"link","url":"https://docs.sentinel-hub.com/api/latest/evalscript/v3/","position":{"start":{"line":3,"column":1},"end":{"line":3,"column":1}},"children":[{"type":"text","value":"Evalscript","position":{"start":{"line":3,"column":1},"end":{"line":3,"column":1}},"key":"OuQw5TMnQ1"}],"urlSource":"https://docs.sentinel-hub.com/api/latest/evalscript/v3/","key":"MFqSMvxGWj"},{"type":"text","value":" to enable large-scale processing using Batch API.","position":{"start":{"line":3,"column":1},"end":{"line":3,"column":1}},"key":"iK7NCUdmbn"}],"key":"yNgsDwcyKP"},{"type":"paragraph","position":{"start":{"line":5,"column":1},"end":{"line":5,"column":1}},"children":[{"type":"text","value":"Here we will import the Evalscript and format it in a way suitable for use with Python:","position":{"start":{"line":5,"column":1},"end":{"line":5,"column":1}},"key":"DD7f5rBka1"}],"key":"OSBUcJBJAz"},{"type":"list","ordered":false,"spread":false,"position":{"start":{"line":7,"column":1},"end":{"line":8,"column":1}},"children":[{"type":"listItem","spread":true,"position":{"start":{"line":7,"column":1},"end":{"line":7,"column":1}},"children":[{"type":"text","value":"the variables ","position":{"start":{"line":7,"column":1},"end":{"line":7,"column":1}},"key":"fDjpUpR7Oh"},{"type":"inlineCode","value":"YEAR0","position":{"start":{"line":7,"column":1},"end":{"line":7,"column":1}},"key":"UHOe1DoQsN"},{"type":"text","value":" and ","position":{"start":{"line":7,"column":1},"end":{"line":7,"column":1}},"key":"n0HU9wE7mR"},{"type":"inlineCode","value":"YEAR1","position":{"start":{"line":7,"column":1},"end":{"line":7,"column":1}},"key":"h8wwaKbosf"},{"type":"text","value":" will be replaced by ","position":{"start":{"line":7,"column":1},"end":{"line":7,"column":1}},"key":"kYxa09MQQH"},{"type":"inlineCode","value":"{0}","position":{"start":{"line":7,"column":1},"end":{"line":7,"column":1}},"key":"eOOyhtxD0C"},{"type":"text","value":" and ","position":{"start":{"line":7,"column":1},"end":{"line":7,"column":1}},"key":"Tmdif168jv"},{"type":"inlineCode","value":"{1}","position":{"start":{"line":7,"column":1},"end":{"line":7,"column":1}},"key":"wY1g22uoHj"},{"type":"text","value":" for Python to pass the parameters","position":{"start":{"line":7,"column":1},"end":{"line":7,"column":1}},"key":"NzjX2OtDyD"}],"key":"sA3bi6iShE"},{"type":"listItem","spread":true,"position":{"start":{"line":8,"column":1},"end":{"line":8,"column":1}},"children":[{"type":"text","value":"the ","position":{"start":{"line":8,"column":1},"end":{"line":8,"column":1}},"key":"Y5YYM0MEA9"},{"type":"inlineCode","value":"{","position":{"start":{"line":8,"column":1},"end":{"line":8,"column":1}},"key":"B5X4bZopKP"},{"type":"text","value":" and ","position":{"start":{"line":8,"column":1},"end":{"line":8,"column":1}},"key":"uENhg5WIMg"},{"type":"inlineCode","value":"}","position":{"start":{"line":8,"column":1},"end":{"line":8,"column":1}},"key":"H0iQTOJHnT"},{"type":"text","value":" in the Evalscript will be escaped to ","position":{"start":{"line":8,"column":1},"end":{"line":8,"column":1}},"key":"wofhxHMckL"},{"type":"inlineCode","value":"{{","position":{"start":{"line":8,"column":1},"end":{"line":8,"column":1}},"key":"Dc68ZF1yp8"},{"type":"text","value":" and ","position":{"start":{"line":8,"column":1},"end":{"line":8,"column":1}},"key":"D32FFAN4hP"},{"type":"inlineCode","value":"}}","position":{"start":{"line":8,"column":1},"end":{"line":8,"column":1}},"key":"MnE3pXK7vn"}],"key":"tJc94TmRne"}],"key":"aFnqy7UBQ4"}],"key":"F4JiKFVNag"},{"type":"block","kind":"notebook-code","data":{},"children":[{"type":"code","lang":"python","executable":true,"value":"# Open evalscript\nhttp = urllib3.PoolManager()\nresponse = http.request('GET', \"https://raw.githubusercontent.com/eurodatacube/notebooks/master/notebooks/contributions/example_data/drought_monitoring/mrvpp_500m_monthly_annual_raster_stats.js\")\nevalscript_mrvpp = response.data.decode('utf-8')\n\n# Make replacements\nevalscript_mrvpp = evalscript_mrvpp.replace('{', '{{')\nevalscript_mrvpp = evalscript_mrvpp.replace('}', '}}')\nevalscript_mrvpp = evalscript_mrvpp.replace('YEAR0', '{0}')\nevalscript_mrvpp = evalscript_mrvpp.replace('YEAR1', '{1}')","key":"a8VEUK0JxF"},{"type":"output","id":"Qnzpl4quE4LN9At1wioPu","data":[],"key":"XF0ysR1jtd"}],"key":"SbYvzIB4Aq"},{"type":"block","kind":"notebook-content","data":{},"children":[{"type":"heading","depth":2,"position":{"start":{"line":1,"column":1},"end":{"line":1,"column":1}},"children":[{"type":"text","value":"Run first Batch request","position":{"start":{"line":1,"column":1},"end":{"line":1,"column":1}},"key":"WmsQH2ZHD8"}],"identifier":"run-first-batch-request","label":"Run first Batch request","html_id":"run-first-batch-request","implicit":true,"key":"E2XRBKth8Q"}],"key":"OEP58zIx22"},{"type":"block","kind":"notebook-content","data":{},"children":[{"type":"heading","depth":3,"position":{"start":{"line":1,"column":1},"end":{"line":1,"column":1}},"children":[{"type":"text","value":"Set CreoDIAS bucket name","position":{"start":{"line":1,"column":1},"end":{"line":1,"column":1}},"key":"vC1jNyTLJd"}],"identifier":"set-creodias-bucket-name","label":"Set CreoDIAS bucket name","html_id":"set-creodias-bucket-name","implicit":true,"key":"GsLa5yqUmN"},{"type":"paragraph","position":{"start":{"line":3,"column":1},"end":{"line":3,"column":1}},"children":[{"type":"text","value":"Set the name of the bucket (that was ","position":{"start":{"line":3,"column":1},"end":{"line":3,"column":1}},"key":"I88Yr7m6IP"},{"type":"link","url":"https://docs.sentinel-hub.com/api/latest/api/batch/#aws-bucket-settings","position":{"start":{"line":3,"column":1},"end":{"line":3,"column":1}},"children":[{"type":"text","value":"correctly setup","position":{"start":{"line":3,"column":1},"end":{"line":3,"column":1}},"key":"vaIWZLgWCq"}],"urlSource":"https://docs.sentinel-hub.com/api/latest/api/batch/#aws-bucket-settings","key":"qBDHEUc1eR"},{"type":"text","value":") where the results will be saved.","position":{"start":{"line":3,"column":1},"end":{"line":3,"column":1}},"key":"fP8004bjQD"}],"key":"XaJYpXs3HD"}],"key":"yJld6emQ6R"},{"type":"block","kind":"notebook-code","data":{},"children":[{"type":"code","lang":"python","executable":true,"value":"BUCKET_NAME = '<BUCKET-NAME>'","key":"mHxezd3Z2U"},{"type":"output","id":"2eGcuww0mOPJ_XaO5uB6Z","data":[],"key":"wmYJqYoct6"}],"key":"odVC2kZhKe"},{"type":"block","kind":"notebook-content","data":{},"children":[{"type":"heading","depth":3,"position":{"start":{"line":1,"column":1},"end":{"line":1,"column":1}},"children":[{"type":"text","value":"Set input data collection IDs","position":{"start":{"line":1,"column":1},"end":{"line":1,"column":1}},"key":"Y1GiRWQwSy"}],"identifier":"set-input-data-collection-ids","label":"Set input data collection IDs","html_id":"set-input-data-collection-ids","implicit":true,"key":"iJFJjmwYnZ"},{"type":"paragraph","position":{"start":{"line":3,"column":1},"end":{"line":3,"column":1}},"children":[{"type":"text","value":"For the first step, we will three input layers that are hosted on CreoDIAS / WEkEO.","position":{"start":{"line":3,"column":1},"end":{"line":3,"column":1}},"key":"MrXDXaYHzm"}],"key":"oAJua2RpXL"},{"type":"list","ordered":false,"spread":false,"position":{"start":{"line":5,"column":1},"end":{"line":8,"column":1}},"children":[{"type":"listItem","spread":true,"position":{"start":{"line":5,"column":1},"end":{"line":5,"column":1}},"children":[{"type":"link","url":"https://edo.jrc.ec.europa.eu/documents/factsheets/factsheet_soilmoisture.pdf","position":{"start":{"line":5,"column":1},"end":{"line":5,"column":1}},"children":[{"type":"text","value":"Soil moisture index and anomaly","position":{"start":{"line":5,"column":1},"end":{"line":5,"column":1}},"key":"iQMujEFYwj"}],"urlSource":"https://edo.jrc.ec.europa.eu/documents/factsheets/factsheet_soilmoisture.pdf","key":"DCl7NbL2NV"}],"key":"cm8LbpDdss"},{"type":"listItem","spread":true,"position":{"start":{"line":6,"column":1},"end":{"line":6,"column":1}},"children":[{"type":"link","url":"https://www.eea.europa.eu/data-and-maps/data/copernicus-land-monitoring-service-medium","position":{"start":{"line":6,"column":1},"end":{"line":6,"column":1}},"children":[{"type":"text","value":"MR-VPP","position":{"start":{"line":6,"column":1},"end":{"line":6,"column":1}},"key":"A4zOIZGHpn"}],"urlSource":"https://www.eea.europa.eu/data-and-maps/data/copernicus-land-monitoring-service-medium","key":"Ly5gZJ8p6u"}],"key":"sjH3Pi8n67"},{"type":"listItem","spread":true,"position":{"start":{"line":7,"column":1},"end":{"line":8,"column":1}},"children":[{"type":"text","value":"Statistical indices: a combination of ","position":{"start":{"line":7,"column":1},"end":{"line":7,"column":1}},"key":"pdwDrtmoyG"},{"type":"link","url":"https://ec.europa.eu/eurostat/web/nuts/background","position":{"start":{"line":7,"column":1},"end":{"line":7,"column":1}},"children":[{"type":"text","value":"NUTS3","position":{"start":{"line":7,"column":1},"end":{"line":7,"column":1}},"key":"n0pwuWQRBn"}],"urlSource":"https://ec.europa.eu/eurostat/web/nuts/background","key":"Bgsa7B7iJL"},{"type":"text","value":", ","position":{"start":{"line":7,"column":1},"end":{"line":7,"column":1}},"key":"QQdbwkboip"},{"type":"link","url":"https://www.eea.europa.eu/data-and-maps/data/corine-land-cover-accounting-layers","position":{"start":{"line":7,"column":1},"end":{"line":7,"column":1}},"children":[{"type":"text","value":"CLCA","position":{"start":{"line":7,"column":1},"end":{"line":7,"column":1}},"key":"X3YOgrl2bY"}],"urlSource":"https://www.eea.europa.eu/data-and-maps/data/corine-land-cover-accounting-layers","key":"V62M5Fojvk"},{"type":"text","value":", and ","position":{"start":{"line":7,"column":1},"end":{"line":7,"column":1}},"key":"ucOVeg9A31"},{"type":"link","url":"https://www.eea.europa.eu/data-and-maps/data/land-cover-flows-based-on","position":{"start":{"line":7,"column":1},"end":{"line":7,"column":1}},"children":[{"type":"text","value":"Land Cover Flow 2000-2018","position":{"start":{"line":7,"column":1},"end":{"line":7,"column":1}},"key":"vlrtyn0Fw0"}],"urlSource":"https://www.eea.europa.eu/data-and-maps/data/land-cover-flows-based-on","key":"oJgtSCZApz"},{"type":"text","value":".","position":{"start":{"line":7,"column":1},"end":{"line":7,"column":1}},"key":"kugBjGhL63"}],"key":"RzKv1Cj78v"}],"key":"iMbElqZYIP"},{"type":"paragraph","position":{"start":{"line":9,"column":1},"end":{"line":9,"column":1}},"children":[{"type":"text","value":"Please contact us if you need access to these data collections: ","position":{"start":{"line":9,"column":1},"end":{"line":9,"column":1}},"key":"mjc8E571yR"},{"type":"inlineCode","value":"info@sentinel-hub.com","position":{"start":{"line":9,"column":1},"end":{"line":9,"column":1}},"key":"SsFALAlugT"},{"type":"text","value":".","position":{"start":{"line":9,"column":1},"end":{"line":9,"column":1}},"key":"hFuqxRl0HC"}],"key":"yElgNQ8IkD"}],"key":"D8DJ9kTQE8"},{"type":"block","kind":"notebook-code","data":{},"children":[{"type":"code","lang":"python","executable":true,"value":"# Set collection IDs for the input layers\nsoil_moisture_id = \"<ID>\"\nmrvpp_timesat_id = \"<ID>\"\nstatistical_areas_id = \"<ID>\"","key":"GzPKVH8lZj"},{"type":"output","id":"g6blZT0ORhJD8-zAXLPu9","data":[],"key":"tvERXVgoyg"}],"key":"KOf8iZh6P7"},{"type":"block","kind":"notebook-content","data":{},"children":[{"type":"heading","depth":3,"position":{"start":{"line":1,"column":1},"end":{"line":1,"column":1}},"children":[{"type":"text","value":"Requests for Batch","position":{"start":{"line":1,"column":1},"end":{"line":1,"column":1}},"key":"tqDGCWeU1f"}],"identifier":"requests-for-batch","label":"Requests for Batch","html_id":"requests-for-batch","implicit":true,"key":"JX2FFvDlEx"},{"type":"paragraph","position":{"start":{"line":3,"column":1},"end":{"line":3,"column":1}},"children":[{"type":"text","value":"In the next cell we prepare a function to run Batch Processing so that we can easily trigger over many years.","position":{"start":{"line":3,"column":1},"end":{"line":3,"column":1}},"key":"QwuCOX9mun"}],"key":"mqSxZ4k1tb"}],"key":"r7sJc7oeAO"},{"type":"block","kind":"notebook-code","data":{},"children":[{"type":"code","lang":"python","executable":true,"value":"def run_batch_year(thisyear, aoi, evalscript, foldername, myconfig):\n    \n    print(f\"Running Year {thisyear}\")\n        \n    # Set timesat dates\n    timesat_start_date = dt.date(thisyear, 1, 1)\n    timesat_end_date = dt.date(thisyear, 1, 1)\n\n    # Automatically calculate Soil moisture dates\n    sm_start_date = timesat_start_date.replace(year=timesat_start_date.year-1)\n    sm_end_date = dt.date(timesat_end_date.year, 12, 31)\n    \n    # Batch object\n    batch = SentinelHubBatch(config=myconfig)\n    \n    # Make the outputs\n    shresponses = [SentinelHubRequest.output_response(f'Monthly_Drought_Hazard_{x}_{y}', MimeType.TIFF) for y in range(1,12+1) for x in [str(thisyear-1), thisyear]]\n    shresponses.append(SentinelHubRequest.output_response(f'Annual_Soil_Moisture_{thisyear}', MimeType.TIFF))\n    shresponses.append(SentinelHubRequest.output_response(f'Annual_Drought_Pressure_{thisyear}', MimeType.TIFF))\n    shresponses.append(SentinelHubRequest.output_response(f'Drought_Pressure_Month_{thisyear}', MimeType.TIFF))\n    shresponses.append(SentinelHubRequest.output_response(f'Annual_Drought_Pressure_Intensity_{thisyear}', MimeType.TIFF))\n    shresponses.append(SentinelHubRequest.output_response(f'LINT_anomaly_{thisyear}', MimeType.TIFF))\n    shresponses.append(SentinelHubRequest.output_response(f'Drought_Impact_{thisyear}', MimeType.TIFF))\n    shresponses.append(SentinelHubRequest.output_response(f'Drought_Impact_Mask_{thisyear}', MimeType.TIFF))\n    shresponses.append(SentinelHubRequest.output_response(f'Drought_Impact_Intensity_{thisyear}', MimeType.TIFF))\n    shresponses.append(SentinelHubRequest.output_response(f'Drought_Impact_Intensity_Mask_{thisyear}', MimeType.TIFF))\n    shresponses.append(SentinelHubRequest.output_response(f'userdata', MimeType.JSON))\n\n    \n    # Make the request for Batch\n    request_for_batch = SentinelHubRequest(\n        evalscript=evalscript.format(str(thisyear-1), str(thisyear)),\n        input_data=[\n        SentinelHubRequest.input_data(\n            data_collection=DataCollection.define_byoc(soil_moisture_id),          \n            identifier=\"SM\",\n            time_interval=(sm_start_date, sm_end_date),          \n        ),\n       SentinelHubRequest.input_data(\n            data_collection=DataCollection.define_byoc(mrvpp_timesat_id),          \n            identifier=\"TIMESAT\",\n            time_interval=(timesat_start_date, timesat_end_date),          \n        ),\n        SentinelHubRequest.input_data(\n            data_collection=DataCollection.define_byoc(mrvpp_timesat_id),          \n            identifier=\"TIMESATLONG\",\n            time_interval=(dt.date(2000, 1, 1), dt.date(2021, 1, 1)),          \n        ),\n        SentinelHubRequest.input_data(\n            data_collection=DataCollection.define_byoc(statistical_areas_id),          \n            identifier=\"INDICES\",\n            time_interval=(dt.date(2018, 1, 1), dt.date(2018, 1, 1)),          \n        ),\n    ],\n        responses=shresponses,\n        geometry=aoi,\n        config=myconfig\n    )\n    \n    # Create Batch request\n    batch_request = batch.create(\n        request_for_batch,\n        tiling_grid=SentinelHubBatch.tiling_grid(\n            grid_id=6,\n            resolution=500,\n            buffer=(0, 0)\n        ),\n        description=f'EEA MRVPP FULL 500m year {thisyear}',\n        output = SentinelHubBatch.output(\n        defaultTilePath = f\"s3://{BUCKET_NAME}/{foldername}\",\n        cog_output = True,\n        create_collection = False,\n        cog_parameters = {\"resamplingAlgorithm\": \"nearest\"}\n        )\n    )\n    \n    time.sleep(15)\n    \n    batch_request = batch.get_request(batch_request)\n    \n    batch.start_analysis(batch_request)\n    \n    batch_request = batch.get_request(batch_request)\n    \n   \n   \n    batch_request = batch.get_request(batch_request)\n    status = 0\n    cnt = 0\n    \n    while status == 0:\n\n        time.sleep(15)\n        \n        batch_request = batch.get_request(batch_request)\n\n        if batch_request.status == BatchRequestStatus.ANALYSIS_DONE:\n            status = 1\n            failed = False\n            print(\"Analysis done\")\n        elif batch_request.status == BatchRequestStatus.FAILED:\n            status = 1\n            failed = True\n            print(\"Failed\")\n        elif batch_request.status == BatchRequestStatus.ANALYSING:\n            status = 0\n            print(\"Still analysing\")\n            time.sleep(5)\n        else:\n            status = 0\n            time.sleep(5)\n            cnt += 1\n            print(f\"Ping number: {cnt}\")\n        \n    if not failed:\n        batch_request = batch.get_request(batch_request)\n        batch.start_job(batch_request)\n        print(f\"Running {batch_request.request_id}\")\n    else:\n        raise RuntimeError(\"Batch failed to analyse\")\n    batch_request = batch.get_request(batch_request)    \n    return batch_request.request_id","key":"KKHHZhmTk2"},{"type":"output","id":"R-tkLz19WsIwIixZkRQUL","data":[],"key":"PLXkrduFV9"}],"key":"pJiZavn9uj"},{"type":"block","kind":"notebook-content","data":{},"children":[{"type":"heading","depth":3,"position":{"start":{"line":1,"column":1},"end":{"line":1,"column":1}},"children":[{"type":"text","value":"Run the Batch Processing","position":{"start":{"line":1,"column":1},"end":{"line":1,"column":1}},"key":"EkenWNwnUc"}],"identifier":"run-the-batch-processing","label":"Run the Batch Processing","html_id":"run-the-batch-processing","implicit":true,"key":"logAAFMvEV"}],"key":"oKWqnmo0Qw"},{"type":"block","kind":"notebook-code","data":{},"children":[{"type":"code","lang":"python","executable":true,"value":"# Collect information about the Batch Process in a list\nids = []","key":"XhNGqTCbb3"},{"type":"output","id":"oeahY4YXQOxjrmLaYqV-y","data":[],"key":"FjBrXdWoqi"}],"key":"WlndhxY4lZ"},{"type":"block","kind":"notebook-code","data":{"tags":[]},"children":[{"type":"code","lang":"python","executable":true,"value":"# Loop from 2000 to 2003 for this example\nfor x in list(range(2000, 2022)):\n    ids.append(run_batch_year(x, cadiz_aoi, evalscript_mrvpp, \"MRVPP_FULL_ANNUAL_MONTHLY\", config))","visibility":"show","key":"iLE9kR5Ioa"},{"type":"output","id":"3ccwYawhLlIIfclWxuDkb","data":[],"visibility":"show","key":"sypAmTzCrC"}],"visibility":"show","key":"UiVcAwSjdi"},{"type":"block","kind":"notebook-content","data":{},"children":[{"type":"heading","depth":2,"position":{"start":{"line":1,"column":1},"end":{"line":1,"column":1}},"children":[{"type":"text","value":"Step 2: MR-VPP long term average products","position":{"start":{"line":1,"column":1},"end":{"line":1,"column":1}},"key":"EGbpAQV9sk"}],"identifier":"step-2-mr-vpp-long-term-average-products","label":"Step 2: MR-VPP long term average products","html_id":"step-2-mr-vpp-long-term-average-products","implicit":true,"key":"R20Y1jJ3jF"},{"type":"paragraph","position":{"start":{"line":3,"column":1},"end":{"line":3,"column":1}},"children":[{"type":"text","value":"In a second step, we will compute the long term average drought products based on the Medium Resolution Vegetation Phenology and Productivity (MR-VPP) products.","position":{"start":{"line":3,"column":1},"end":{"line":3,"column":1}},"key":"RG8NaJRx5I"}],"key":"lkdbT0wW5f"}],"key":"XCdkFl1g6B"},{"type":"block","kind":"notebook-content","data":{},"children":[{"type":"heading","depth":3,"position":{"start":{"line":1,"column":1},"end":{"line":1,"column":1}},"children":[{"type":"text","value":"Set input data collection IDs","position":{"start":{"line":1,"column":1},"end":{"line":1,"column":1}},"key":"v2712bpSrf"}],"identifier":"set-input-data-collection-ids","label":"Set input data collection IDs","html_id":"set-input-data-collection-ids-1","implicit":true,"key":"roffpl6UTW"},{"type":"paragraph","position":{"start":{"line":3,"column":1},"end":{"line":3,"column":1}},"children":[{"type":"text","value":"For the second step, we will reuse three input layers defined in step 1.","position":{"start":{"line":3,"column":1},"end":{"line":3,"column":1}},"key":"SPLT5Czirf"}],"key":"JRmYSooQQC"}],"key":"sVRjBueEfF"},{"type":"block","kind":"notebook-content","data":{},"children":[{"type":"heading","depth":3,"position":{"start":{"line":1,"column":1},"end":{"line":1,"column":1}},"children":[{"type":"text","value":"Evalscript for MR-VPP 500m products","position":{"start":{"line":1,"column":1},"end":{"line":1,"column":1}},"key":"OrZPSKwEtT"}],"identifier":"evalscript-for-mr-vpp-500m-products","label":"Evalscript for MR-VPP 500m products","html_id":"evalscript-for-mr-vpp-500m-products-1","implicit":true,"key":"rlK6b5a9bC"},{"type":"paragraph","position":{"start":{"line":3,"column":1},"end":{"line":3,"column":1}},"children":[{"type":"text","value":"The workflow was written as an ","position":{"start":{"line":3,"column":1},"end":{"line":3,"column":1}},"key":"f9CQzpyA6J"},{"type":"link","url":"https://docs.sentinel-hub.com/api/latest/evalscript/v3/","position":{"start":{"line":3,"column":1},"end":{"line":3,"column":1}},"children":[{"type":"text","value":"Evalscript","position":{"start":{"line":3,"column":1},"end":{"line":3,"column":1}},"key":"vwdX4mlUB3"}],"urlSource":"https://docs.sentinel-hub.com/api/latest/evalscript/v3/","key":"t0jJbOGK3x"},{"type":"text","value":" to enable large-scale processing using Batch API.","position":{"start":{"line":3,"column":1},"end":{"line":3,"column":1}},"key":"Ycq5P4umBe"}],"key":"hohczmIHnT"},{"type":"paragraph","position":{"start":{"line":5,"column":1},"end":{"line":5,"column":1}},"children":[{"type":"text","value":"Here we will import the Evalscript:","position":{"start":{"line":5,"column":1},"end":{"line":5,"column":1}},"key":"BvASl1vQ97"}],"key":"b4rz3Xh72b"}],"key":"Su3XKZwL9V"},{"type":"block","kind":"notebook-code","data":{},"children":[{"type":"code","lang":"python","executable":true,"value":"# Open evalscript\nhttp = urllib3.PoolManager()\nresponse = http.request('GET', \"https://raw.githubusercontent.com/eurodatacube/notebooks/master/notebooks/contributions/example_data/drought_monitoring/mrvpp_500m_lta_raster_stats.js\")\nevalscript_mrvpp_lta = response.data.decode('utf-8')","key":"OJQDTZ54zX"},{"type":"output","id":"yFzWfdBURg4mM0j1i9aS5","data":[],"key":"XOa7msYxJ1"}],"key":"dhIz6GnjEh"},{"type":"block","kind":"notebook-content","data":{},"children":[{"type":"heading","depth":3,"position":{"start":{"line":1,"column":1},"end":{"line":1,"column":1}},"children":[{"type":"text","value":"Create Batch Request","position":{"start":{"line":1,"column":1},"end":{"line":1,"column":1}},"key":"jaYF54wnVR"}],"identifier":"create-batch-request","label":"Create Batch Request","html_id":"create-batch-request","implicit":true,"key":"SBMVasPxcE"}],"key":"uUfWrYM7gv"},{"type":"block","kind":"notebook-code","data":{},"children":[{"type":"code","lang":"python","executable":true,"value":"# Set dates for full range\nstart_date = dt.date(2000, 1, 1)\nend_date = dt.date(2021, 1, 1)\n\n# Batch object\nbatch = SentinelHubBatch(config=config)\n\nrequest_for_batch = SentinelHubRequest(\n    evalscript=evalscript_mrvpp_lta,\n    input_data=[\n        SentinelHubRequest.input_data(\n            data_collection=DataCollection.define_byoc(soil_moisture_id),          \n            identifier=\"SM\",\n            time_interval=(start_date, end_date),          \n        ),\n        SentinelHubRequest.input_data(\n            data_collection=DataCollection.define_byoc(mrvpp_timesat_id),          \n            identifier=\"TIMESAT\",\n            time_interval=(start_date, end_date),          \n        ),\n        SentinelHubRequest.input_data(\n            data_collection=DataCollection.define_byoc(statistical_areas_id),          \n            identifier=\"INDICES\",\n            time_interval=(dt.date(2018, 1, 1), dt.date(2018, 1, 1)),          \n        ),\n    ],\n    responses=[SentinelHubRequest.output_response('Long_Term_Soil_Moisture', MimeType.TIFF),\n               SentinelHubRequest.output_response('Long_Term_Drought_Pressure_Intensity', MimeType.TIFF),\n               SentinelHubRequest.output_response(f'userdata', MimeType.JSON)\n              ],\n    geometry=andalusia_aoi,\n    config=config\n)\n\n# Create Batch request\nbatch_request = batch.create(\n    request_for_batch,\n    tiling_grid=SentinelHubBatch.tiling_grid(\n        grid_id=6,\n        resolution=500,\n        buffer=(0, 0)\n    ),\n    description=f'EEA 500m Long Term Average',\n    output = SentinelHubBatch.output(\n    defaultTilePath = f\"s3://{BUCKET_NAME}/MRVPP_FULL_LTA\",\n    cog_output = True,\n    create_collection = False,\n    cog_parameters = {\"resamplingAlgorithm\": \"nearest\"}\n    )\n)\n\nbatch_request = batch.get_request(batch_request)\n\nprint(batch_request)","key":"Jz9NUqvy3y"},{"type":"output","id":"KWGgPaVxQpRIcSmU0NIc0","data":[],"key":"PYAoXy47ux"}],"key":"SDc7Sgyuth"},{"type":"block","kind":"notebook-code","data":{},"children":[{"type":"code","lang":"python","executable":true,"value":"# Analyse the request\nbatch.start_analysis(batch_request)\n\ntime.sleep(45)\n\nbatch_request = batch.get_request(batch_request)\nprint(batch_request)","key":"sDDg0FFvJw"},{"type":"output","id":"yFBcDf26961ac5JM7csRs","data":[],"key":"BGItQn8LhZ"}],"key":"jgTR40E9Ry"},{"type":"block","kind":"notebook-content","data":{},"children":[{"type":"heading","depth":3,"position":{"start":{"line":1,"column":1},"end":{"line":1,"column":1}},"children":[{"type":"text","value":"Run Batch Request","position":{"start":{"line":1,"column":1},"end":{"line":1,"column":1}},"key":"LBbGa9qJLc"}],"identifier":"run-batch-request","label":"Run Batch Request","html_id":"run-batch-request","implicit":true,"key":"H3nnEF84mL"}],"key":"Q0ejfwCWAE"},{"type":"block","kind":"notebook-code","data":{},"children":[{"type":"code","lang":"python","executable":true,"value":"batch.start_job(batch_request)","key":"s2VFQbCpnv"},{"type":"output","id":"dCnvc8Z59wYMxiYT2KqQ5","data":[],"key":"CkxmkVFRW7"}],"key":"aGddajydQp"},{"type":"block","kind":"notebook-content","data":{},"children":[{"type":"heading","depth":2,"position":{"start":{"line":1,"column":1},"end":{"line":1,"column":1}},"children":[{"type":"text","value":"Step 3: HR-VPP products","position":{"start":{"line":1,"column":1},"end":{"line":1,"column":1}},"key":"SBe5oKaKYr"}],"identifier":"step-3-hr-vpp-products","label":"Step 3: HR-VPP products","html_id":"step-3-hr-vpp-products","implicit":true,"key":"dxlICRHQzp"},{"type":"paragraph","position":{"start":{"line":3,"column":1},"end":{"line":3,"column":1}},"children":[{"type":"text","value":"In the third step, we will compute the products derived from the High Resolution Vegetation Phenology and Productivity (HR-VPP) layers at 10m resolution. The products are derived from a combination of HR-VPP, and the products computed in the previous steps.","position":{"start":{"line":3,"column":1},"end":{"line":3,"column":1}},"key":"PN7XsACFS2"}],"key":"A027qxDBHu"}],"key":"YGbTABlmlw"},{"type":"block","kind":"notebook-content","data":{},"children":[{"type":"heading","depth":3,"position":{"start":{"line":1,"column":1},"end":{"line":1,"column":1}},"children":[{"type":"text","value":"Set input data collection IDs","position":{"start":{"line":1,"column":1},"end":{"line":1,"column":1}},"key":"LriU9L9gRx"}],"identifier":"set-input-data-collection-ids","label":"Set input data collection IDs","html_id":"set-input-data-collection-ids-2","implicit":true,"key":"JbcaH1u9wZ"},{"type":"paragraph","position":{"start":{"line":3,"column":1},"end":{"line":3,"column":1}},"children":[{"type":"text","value":"For the last step, we will use four input layers that are hosted on CreoDIAS / WEkEO.","position":{"start":{"line":3,"column":1},"end":{"line":3,"column":1}},"key":"HL7ZONtRpL"}],"key":"kWzcYFm2St"},{"type":"list","ordered":false,"spread":false,"position":{"start":{"line":5,"column":1},"end":{"line":9,"column":1}},"children":[{"type":"listItem","spread":true,"position":{"start":{"line":5,"column":1},"end":{"line":5,"column":1}},"children":[{"type":"link","url":"https://land.copernicus.eu/pan-european/biophysical-parameters/high-resolution-vegetation-phenology-and-productivity","position":{"start":{"line":5,"column":1},"end":{"line":5,"column":1}},"children":[{"type":"text","value":"HR-VPP season 1","position":{"start":{"line":5,"column":1},"end":{"line":5,"column":1}},"key":"MBhsVetJJS"}],"urlSource":"https://land.copernicus.eu/pan-european/biophysical-parameters/high-resolution-vegetation-phenology-and-productivity","key":"txjZiFai9b"},{"type":"text","value":": the data for the first season of each year.","position":{"start":{"line":5,"column":1},"end":{"line":5,"column":1}},"key":"Hz6vu41gi6"}],"key":"Eko3QSqup0"},{"type":"listItem","spread":true,"position":{"start":{"line":6,"column":1},"end":{"line":6,"column":1}},"children":[{"type":"link","url":"https://land.copernicus.eu/pan-european/biophysical-parameters/high-resolution-vegetation-phenology-and-productivity","position":{"start":{"line":6,"column":1},"end":{"line":6,"column":1}},"children":[{"type":"text","value":"HR-VPP season 2","position":{"start":{"line":6,"column":1},"end":{"line":6,"column":1}},"key":"KlegqthIeQ"}],"urlSource":"https://land.copernicus.eu/pan-european/biophysical-parameters/high-resolution-vegetation-phenology-and-productivity","key":"D12AhZ9xhW"},{"type":"text","value":": the data for the second season of each year.","position":{"start":{"line":6,"column":1},"end":{"line":6,"column":1}},"key":"m8oFPzoKfr"}],"key":"gs1pvupvjd"},{"type":"listItem","spread":true,"position":{"start":{"line":7,"column":1},"end":{"line":7,"column":1}},"children":[{"type":"text","value":"Statistical indices: a combination of ","position":{"start":{"line":7,"column":1},"end":{"line":7,"column":1}},"key":"nohWw8nmOI"},{"type":"link","url":"https://ec.europa.eu/eurostat/web/nuts/background","position":{"start":{"line":7,"column":1},"end":{"line":7,"column":1}},"children":[{"type":"text","value":"NUTS3","position":{"start":{"line":7,"column":1},"end":{"line":7,"column":1}},"key":"ZHwxPZ5Ex9"}],"urlSource":"https://ec.europa.eu/eurostat/web/nuts/background","key":"iprrENNxeu"},{"type":"text","value":", ","position":{"start":{"line":7,"column":1},"end":{"line":7,"column":1}},"key":"oVpz9UdMH9"},{"type":"link","url":"https://www.eea.europa.eu/data-and-maps/data/corine-land-cover-accounting-layers","position":{"start":{"line":7,"column":1},"end":{"line":7,"column":1}},"children":[{"type":"text","value":"CLCA","position":{"start":{"line":7,"column":1},"end":{"line":7,"column":1}},"key":"M9g1NDprl7"}],"urlSource":"https://www.eea.europa.eu/data-and-maps/data/corine-land-cover-accounting-layers","key":"RMpTq6j0BC"},{"type":"text","value":", and ","position":{"start":{"line":7,"column":1},"end":{"line":7,"column":1}},"key":"RiSeKBviJi"},{"type":"link","url":"https://www.eea.europa.eu/data-and-maps/data/land-cover-flows-based-on","position":{"start":{"line":7,"column":1},"end":{"line":7,"column":1}},"children":[{"type":"text","value":"Land Cover Flow 2000-2018","position":{"start":{"line":7,"column":1},"end":{"line":7,"column":1}},"key":"QzYyqFFYyW"}],"urlSource":"https://www.eea.europa.eu/data-and-maps/data/land-cover-flows-based-on","key":"wzaeP4Yp2x"},{"type":"text","value":".","position":{"start":{"line":7,"column":1},"end":{"line":7,"column":1}},"key":"OJjsGYChxC"}],"key":"qPww5jF4fz"},{"type":"listItem","spread":true,"position":{"start":{"line":8,"column":1},"end":{"line":9,"column":1}},"children":[{"type":"text","value":"Previous Yearly MR-VPP results. After running the first steps, the results need to be ingested as ","position":{"start":{"line":8,"column":1},"end":{"line":8,"column":1}},"key":"I2qt226ijL"},{"type":"link","url":"https://docs.sentinel-hub.com/api/latest/api/byoc/","position":{"start":{"line":8,"column":1},"end":{"line":8,"column":1}},"children":[{"type":"text","value":"BYOC layers","position":{"start":{"line":8,"column":1},"end":{"line":8,"column":1}},"key":"KOMPcRrEks"}],"urlSource":"https://docs.sentinel-hub.com/api/latest/api/byoc/","key":"IPrh9C9vBv"},{"type":"text","value":" in CreoDIAS / WEkEO.","position":{"start":{"line":8,"column":1},"end":{"line":8,"column":1}},"key":"kcs8NUUk3W"}],"key":"jmGyrybJ9p"}],"key":"qcTW0pkPWZ"},{"type":"paragraph","position":{"start":{"line":10,"column":1},"end":{"line":10,"column":1}},"children":[{"type":"text","value":"Please contact us if you need access to these data collections: ","position":{"start":{"line":10,"column":1},"end":{"line":10,"column":1}},"key":"a3zQwyNoGj"},{"type":"inlineCode","value":"info@sentinel-hub.com","position":{"start":{"line":10,"column":1},"end":{"line":10,"column":1}},"key":"Vs6rYNTqYn"},{"type":"text","value":".","position":{"start":{"line":10,"column":1},"end":{"line":10,"column":1}},"key":"eKR6EGrveI"}],"key":"b0EZZtmOWL"}],"key":"CQZykSilpZ"},{"type":"block","kind":"notebook-code","data":{},"children":[{"type":"code","lang":"python","executable":true,"value":"# Set collection IDs for the input layers\nhrvpp_s1_id = \"<ID>\"\nhrvpp_s2_id = \"<ID>\"\nstatistical_areas_id = \"<ID>\"\nmrvpp_outputs_id = \"<ID>\"","key":"BkqL8Lxc1W"},{"type":"output","id":"qdacFkVrbEzt92q8dwo8-","data":[],"key":"t5x7TAoqOq"}],"key":"N1b2Ru17TY"},{"type":"block","kind":"notebook-content","data":{},"children":[{"type":"heading","depth":2,"position":{"start":{"line":1,"column":1},"end":{"line":1,"column":1}},"children":[{"type":"text","value":"Evalscript for MR-VPP 500m products","position":{"start":{"line":1,"column":1},"end":{"line":1,"column":1}},"key":"lM85i9p9VF"}],"identifier":"evalscript-for-mr-vpp-500m-products","label":"Evalscript for MR-VPP 500m products","html_id":"evalscript-for-mr-vpp-500m-products-2","implicit":true,"key":"SlSOPJIkYJ"},{"type":"paragraph","position":{"start":{"line":3,"column":1},"end":{"line":3,"column":1}},"children":[{"type":"text","value":"The workflow was written as an ","position":{"start":{"line":3,"column":1},"end":{"line":3,"column":1}},"key":"Y8Cn1XOiYg"},{"type":"link","url":"https://docs.sentinel-hub.com/api/latest/evalscript/v3/","position":{"start":{"line":3,"column":1},"end":{"line":3,"column":1}},"children":[{"type":"text","value":"Evalscript","position":{"start":{"line":3,"column":1},"end":{"line":3,"column":1}},"key":"A42xOP38VD"}],"urlSource":"https://docs.sentinel-hub.com/api/latest/evalscript/v3/","key":"b21Y2RLqfj"},{"type":"text","value":" to enable large-scale processing using Batch API.","position":{"start":{"line":3,"column":1},"end":{"line":3,"column":1}},"key":"DIVvid20Iv"}],"key":"LVjVeoyd7N"},{"type":"paragraph","position":{"start":{"line":5,"column":1},"end":{"line":5,"column":1}},"children":[{"type":"text","value":"Here we will import the Evalscript and format it in a way suitable for use with Python:","position":{"start":{"line":5,"column":1},"end":{"line":5,"column":1}},"key":"X60o1iDMel"}],"key":"pSotzJozo5"},{"type":"list","ordered":false,"spread":false,"position":{"start":{"line":7,"column":1},"end":{"line":8,"column":1}},"children":[{"type":"listItem","spread":true,"position":{"start":{"line":7,"column":1},"end":{"line":7,"column":1}},"children":[{"type":"text","value":"the variables ","position":{"start":{"line":7,"column":1},"end":{"line":7,"column":1}},"key":"A0RH5fykeJ"},{"type":"inlineCode","value":"YEAR0","position":{"start":{"line":7,"column":1},"end":{"line":7,"column":1}},"key":"Knfo8NfiX1"},{"type":"text","value":" will be replaced by ","position":{"start":{"line":7,"column":1},"end":{"line":7,"column":1}},"key":"lw8d1gssuX"},{"type":"inlineCode","value":"{0}","position":{"start":{"line":7,"column":1},"end":{"line":7,"column":1}},"key":"bBtHiJu1oo"},{"type":"text","value":" for Python to pass the parameters","position":{"start":{"line":7,"column":1},"end":{"line":7,"column":1}},"key":"pp8BSR9pdR"}],"key":"aMDBO0uc3O"},{"type":"listItem","spread":true,"position":{"start":{"line":8,"column":1},"end":{"line":8,"column":1}},"children":[{"type":"text","value":"the ","position":{"start":{"line":8,"column":1},"end":{"line":8,"column":1}},"key":"pw9GoLSn8b"},{"type":"inlineCode","value":"{","position":{"start":{"line":8,"column":1},"end":{"line":8,"column":1}},"key":"LT5Y8m5KEt"},{"type":"text","value":" and ","position":{"start":{"line":8,"column":1},"end":{"line":8,"column":1}},"key":"ClpQdV30tk"},{"type":"inlineCode","value":"}","position":{"start":{"line":8,"column":1},"end":{"line":8,"column":1}},"key":"NpNV5iU85V"},{"type":"text","value":" in the Evalscript will be escaped to ","position":{"start":{"line":8,"column":1},"end":{"line":8,"column":1}},"key":"k7R6jqCyRL"},{"type":"inlineCode","value":"{{","position":{"start":{"line":8,"column":1},"end":{"line":8,"column":1}},"key":"MZIyE0JiIw"},{"type":"text","value":" and ","position":{"start":{"line":8,"column":1},"end":{"line":8,"column":1}},"key":"tekYSZrjXa"},{"type":"inlineCode","value":"}}","position":{"start":{"line":8,"column":1},"end":{"line":8,"column":1}},"key":"Ue5c9fCnhI"}],"key":"OjA0SZDKx0"}],"key":"dFdsD6uyJK"}],"key":"CaBjQY3E7U"},{"type":"block","kind":"notebook-code","data":{},"children":[{"type":"code","lang":"python","executable":true,"value":"# Open evalscript\nhttp = urllib3.PoolManager()\nresponse = http.request('GET', \"https://raw.githubusercontent.com/eurodatacube/notebooks/master/notebooks/contributions/example_data/drought_monitoring/hrvpp_10m_raster_stats.js\")\nevalscript_hrvpp = response.data.decode('utf-8')\n\n# Make replacements\nevalscript_hrvpp = evalscript_mrvpp.replace('{', '{{')\nevalscript_hrvpp = evalscript_mrvpp.replace('}', '}}')\nevalscript_hrvpp = evalscript_mrvpp.replace('YEAR0', '{0}')","key":"LgWrplbjvt"},{"type":"output","id":"lDFDpozySe-56WI_Wbuhm","data":[],"key":"Dq7LyP8xAd"}],"key":"ZMZLXAYOWF"},{"type":"block","kind":"notebook-content","data":{},"children":[{"type":"heading","depth":3,"position":{"start":{"line":1,"column":1},"end":{"line":1,"column":1}},"children":[{"type":"text","value":"Requests for Batch","position":{"start":{"line":1,"column":1},"end":{"line":1,"column":1}},"key":"TnvbMPelWq"}],"identifier":"requests-for-batch","label":"Requests for Batch","html_id":"requests-for-batch-1","implicit":true,"key":"nLujVf3Rlc"},{"type":"paragraph","position":{"start":{"line":3,"column":1},"end":{"line":3,"column":1}},"children":[{"type":"text","value":"In the next cell we prepare a function to run Batch Processing so that we can easily trigger over many years.","position":{"start":{"line":3,"column":1},"end":{"line":3,"column":1}},"key":"fl1LA1oqcJ"}],"key":"GinVnio892"}],"key":"sDLJUV3cKi"},{"type":"block","kind":"notebook-code","data":{},"children":[{"type":"code","lang":"python","executable":true,"value":"def run_batch_year(inyear, aoi, evalscript, BUCKET_NAME, FOLDER_NAME, myconfig):\n        \n    # Set timesat dates\n    start_date = dt.date(2017, 1, 1)\n    end_date = dt.date(2021, 1, 1)\n\n    # Batch object\n    batch = SentinelHubBatch(config=myconfig)\n    \n    # Test make the outputs for Process API\n    shresponses = [SentinelHubRequest.output_response(f'TPROD_minmax_{inyear}', MimeType.TIFF)]\n    shresponses.append(SentinelHubRequest.output_response(f'SPROD_minmax_{inyear}', MimeType.TIFF))\n    shresponses.append(SentinelHubRequest.output_response(f'Total_Drought_Impact_{inyear}', MimeType.TIFF))\n    shresponses.append(SentinelHubRequest.output_response(f'Seasonal_Drought_Impact_{inyear}', MimeType.TIFF))\n    shresponses.append(SentinelHubRequest.output_response(f'Season_Length_{inyear}', MimeType.TIFF))\n    shresponses.append(SentinelHubRequest.output_response(f'Nb_Seasons_{inyear}', MimeType.TIFF))\n    shresponses.append(SentinelHubRequest.output_response(f'MR_drought_impact_{inyear}', MimeType.TIFF))\n    shresponses.append(SentinelHubRequest.output_response('userdata', MimeType.JSON))\n\n    \n    # Make the request for Batch\n    request_for_batch = SentinelHubRequest(\n        evalscript=evalscript.format(inyear),\n        input_data=[\n            SentinelHubRequest.input_data(\n                data_collection=DataCollection.define_byoc(mrvpp_outputs_id),          \n                identifier=\"MRVPP\",\n                time_interval=(f'{inyear}-01-01', f'{inyear}-01-01'),          \n            ),\n           SentinelHubRequest.input_data(\n                data_collection=DataCollection.define_byoc(hrvpp_s1_id),          \n                identifier=\"VPP1\",\n                time_interval=(start_date, end_date),          \n            ),\n           SentinelHubRequest.input_data(\n                data_collection=DataCollection.define_byoc(hrvpp_s2_id),          \n                identifier=\"VPP2\",\n                time_interval=(start_date, end_date),          \n            ),\n            SentinelHubRequest.input_data(\n                    data_collection=DataCollection.define_byoc(statistical_areas_id),          \n                    identifier=\"INDICES\",\n                    time_interval=('2018-01-01', '2018-01-01'),          \n                ),\n        ],\n        responses=shresponses,\n        geometry=aoi,\n        config=config\n    )\n\n    # Create Batch request\n    batch_request = batch.create(\n        request_for_batch,\n        tiling_grid=SentinelHubBatch.tiling_grid(\n            grid_id=7,\n            resolution=10,\n            buffer=(0, 0)\n        ),\n        description=f'EEA FULL RUN 10m year {inyear}',\n        output = SentinelHubBatch.output(\n        defaultTilePath = f\"s3://{BUCKET_NAME}/{FOLDER_NAME}\",\n        cog_output = True,\n        create_collection = False,\n        cog_parameters = {\"resamplingAlgorithm\": \"nearest\"}\n        )\n    )\n    \n    time.sleep(15)\n    \n    batch_request = batch.get_request(batch_request)\n\n    print(batch_request)\n    \n    batch.start_analysis(batch_request)\n    \n    batch_request = batch.get_request(batch_request)\n    \n   \n   \n    batch_request = batch.get_request(batch_request)\n    status = 0\n    \n    \n    while status == 0:\n\n        time.sleep(15)\n        \n        batch_request = batch.get_request(batch_request)\n\n        if batch_request.status == BatchRequestStatus.ANALYSIS_DONE:\n            status = 1\n            failed = False\n            print(\"Analysis done\")\n        elif batch_request.status == BatchRequestStatus.FAILED:\n            status = 1\n            failed = True\n            print(\"Failed\")\n        elif batch_request.status == BatchRequestStatus.ANALYSING:\n            status = 0\n            print(\"Still analysing\")\n            time.sleep(5)\n        else:\n            print(\"Other status\")\n            status = 0\n            time.sleep(5)\n        \n    if not failed:\n        batch_request = batch.get_request(batch_request)\n        batch.start_job(batch_request)\n        print(f\"Running {batch_request.request_id}\")\n    else:\n        raise RuntimeError(\"Batch failed to analyse\")\n    batch_request = batch.get_request(batch_request)    \n    return batch_request.request_id","key":"z9Bw7eSIbF"},{"type":"output","id":"7ddhKMebxiBjQrHuqZ1g9","data":[],"key":"XouSKRcKAq"}],"key":"e5JFJT1Ntn"},{"type":"block","kind":"notebook-content","data":{},"children":[{"type":"heading","depth":3,"position":{"start":{"line":1,"column":1},"end":{"line":1,"column":1}},"children":[{"type":"text","value":"Run the Batch Processing","position":{"start":{"line":1,"column":1},"end":{"line":1,"column":1}},"key":"vJeDwwSvf7"}],"identifier":"run-the-batch-processing","label":"Run the Batch Processing","html_id":"run-the-batch-processing-1","implicit":true,"key":"RzSga1iJ2l"}],"key":"IMlmjy0IWW"},{"type":"block","kind":"notebook-code","data":{},"children":[{"type":"code","lang":"python","executable":true,"value":"# Collect information about the Batch Process in a list\nids = []","key":"GT6eiIFABJ"},{"type":"output","id":"iDmZMqnCuo76FYEIFaiEM","data":[],"key":"z4vKaGBg57"}],"key":"Je0ZVkiXR8"},{"type":"block","kind":"notebook-code","data":{"tags":[]},"children":[{"type":"code","lang":"python","executable":true,"value":"# Loop from 2017 to 2020 for this example\nfor x in list(range(2017, 2021)):\n    ids.append(run_batch_year(x, andalusia_aoi, evalscript_hrvpp_avg, BUCKET_NAME, \"HRVPP_FULL\", config))","visibility":"show","key":"coxs7vvFU8"},{"type":"output","id":"WdFeG8WgVA1y8kyma-KQZ","data":[],"visibility":"show","key":"iiFLfaLpdU"}],"visibility":"show","key":"FrXfzYHRVT"}],"key":"k50VZh3vlV"},"references":{"cite":{"order":[],"data":{}}},"footer":{"navigation":{"prev":{"title":"Detect Trucks using Sentinel-2 data","url":"/external-notebooks/eurodatacube/notebooks/notebooks/contributions/detect-trucks-sentinel2","group":"Contributions"},"next":{"title":"Custom Script Contest – Urban Growth in Africa","url":"/external-notebooks/eurodatacube/notebooks/notebooks/contributions/edc-africa-cube-africa-custom-contest","group":"Contributions"}}},"domain":"http://localhost:3000"}